IOmatchbox/IOTEC.py
IOmatchbox/IOmatchbox.py
IOmatchbox/__init__.py
iomatchbox-0.26.dist-info/LICENSE
iomatchbox-0.26.dist-info/METADATA
iomatchbox-0.26.dist-info/WHEEL
iomatchbox-0.26.dist-info/top_level.txt
iomatchbox-0.26.dist-info/RECORD
