Metadata-Version: 2.2
Name: IOmatchbox
Version: 0.26
Summary: Functions and examples to control Integrated Optics CW lasers and standalone TECs through serial commands with Python
Author-email: iancynk <ian.cynk@posteo.eu>
Project-URL: Homepage, https://github.com/iancynk/IOmatchbox
Project-URL: Bug Tracker, https://github.com/iancynk/IOmatchbox/issues
Classifier: Programming Language :: Python :: 3
Classifier: License :: OSI Approved :: MIT License
Classifier: Operating System :: POSIX :: Linux
Classifier: Intended Audience :: Education
Classifier: Intended Audience :: Science/Research
Classifier: Topic :: Scientific/Engineering
Classifier: Topic :: Scientific/Engineering :: Physics
Classifier: Topic :: Software Development :: Libraries
Classifier: Topic :: Software Development :: Libraries :: Python Modules
Requires-Python: >=3.7
License-File: LICENSE
